heyfastqlib/__init__.py
heyfastqlib/_version.py
heyfastqlib/argparse_types.py
heyfastqlib/command.py
heyfastqlib/io.py
heyfastqlib/pipelines.py
heyfastqlib/read.py
heyfastqlib/seqs.py
heyfastqlib/util.py
heyfastq-0.2.2.dist-info/METADATA
heyfastq-0.2.2.dist-info/WHEEL
heyfastq-0.2.2.dist-info/entry_points.txt
heyfastq-0.2.2.dist-info/top_level.txt
heyfastq-0.2.2.dist-info/RECORD
