Metadata-Version: 2.4
Name: heyfastq
Version: 0.2.2
Summary: FASTQ utilities
Author-email: Kyle Bittinger <kylebittinger@gmail.com>
Project-URL: Homepage, https://github.com/kylebittinger/heyfastq
Project-URL: Bug Tracker, https://github.com/kylebittinger/heyfastq/issues
Classifier: Programming Language :: Python :: 3
Classifier: License :: OSI Approved :: MIT License
Classifier: Operating System :: OS Independent
Requires-Python: >=3.10
Provides-Extra: test
Requires-Dist: pytest; extra == "test"
Requires-Dist: pytest-cov; extra == "test"
Provides-Extra: dev
Requires-Dist: pytest; extra == "dev"
Requires-Dist: black; extra == "dev"
